{
  "status": "completed",
  "generated_at": "2026-04-07T23:23:07.603736",
  "duration_seconds": 43.9,
  "duration_human": "0 دقيقة و 43 ثانية",
  "memos_downloaded": 2,
  "memos_sources": {
    "direct": 2,
    "google": 0,
    "builtin_fallback": "نعم — 120+ عبارة مدمجة"
  },
  "total_phrases": 102,
  "categories": {
    "افتتاحيات": {
      "count": 8,
      "top_3": [
        "السيد المستشار / رئيس المحكمة الموقرة",
        "مقدمه من: ______ (المدعي / المتهم / الطاعن)",
        "بعد التحية والتقدير، يتشرف المدعي بعرض الآتي على عدالة المحكمة الموقرة:"
      ]
    },
    "بدايات_دفوع": {
      "count": 21,
      "top_3": [
        "وحيث أن قضاء هذه المحكمة مستقر على ان تقدير جدية التحريات هو من المسائل الموضوعية التى وكل الامر فيها الى سلطة التحقيق تحت إشرا",
        "إذ أن ذلك خاضع لرقابة محكمة الموضوع .   (الطعن رقم 1951 لسنة 48 ق جلسة 15 3 1998 )   السبب الخامس:-   عدم بيان محرر محضر التح",
        "إذ أن مسلك المتهم على مستوى الحيطة والحذر الذى يسلكه الشخص المعتاد  2. الدفع بانقطاع رابطة السببية بين الفعل والنتيجة. ثانيا"
      ]
    },
    "روابط_منطقية": {
      "count": 17,
      "top_3": [
        "والحال كذلك خلو الدعوى من ثمة دليل يمكن الاستناد اليه فى ادانة المتهم و",
        "ومن ثم فإنه يجب لسلامة الحكم بالإدانة فى جريمة القتل الخطأ أن يبين – فضلاً عن مؤدى الأدلة",
        "ومن ثم فإن ما ذهب إليه الحكم المطعون فيه يكون قد جانبه الصواب."
      ]
    },
    "رد_على_الخصم": {
      "count": 13,
      "top_3": [
        "ولا يقدح في ذلك أن سلطة التحقيق صاحبة الحق في إصدار الامر بالتفتيش قد قررت جدية تلك التحريات إذ أن ذلك خاضع لرقابة م",
        "ومردود عليه بأن هذا الدفع لا أساس له من القانون أو الواقع.",
        "ولا ينال من ذلك ما تمسك به الخصم من أن..."
      ]
    },
    "عبارات_أدلة": {
      "count": 12,
      "top_3": [
        "والثابت من الأوراق والمستندات المقدمة أن...",
        "ويؤيد ذلك ما جاء بتقرير الخبير المنتدب من أن...",
        "والدليل على ذلك ما ورد بمحضر الضبط المؤرخ..."
      ]
    },
    "عبارات_استنتاج": {
      "count": 10,
      "top_3": [
        "الأمر الذي يستوجب معه القضاء ببراءة المتهم مما أُسند إليه.",
        "مما يقطع بأن الاتهام المنسوب جاء على غير سند من القانون أو الواقع.",
        "وهو ما يستوجب نقض الحكم المطعون فيه والقضاء مجدداً بـ..."
      ]
    },
    "طلبات_ختامية": {
      "count": 11,
      "top_3": [
        "نلتمس من عدالة المحكمة الحكم وفقاً لما تتخيره الأفضل من الأسباب :  ببراءة المتهم مما اسند إلية تأسيساعلى  أولا: انعدام ركن الخطأ من جا",
        "يلتمس الدفاع من عدالة المحكمة الموقرة القضاء بـ:",
        "بناءً على ما تقدم من أسباب ودفوع ومستندات، نلتمس من هيئة المحكمة الموقرة:"
      ]
    },
    "تقنيات_اقناع": {
      "count": 10,
      "top_3": [
        "وعلة التشريع من وراء هذا النص هي حماية...",
        "والحكمة التي ابتغاها المشرّع من هذا الحكم هي...",
        "ومقتضى العدالة يوجب أن..."
      ]
    }
  },
  "blacklist_check": "passed — 0 مصطلحات غير قطرية",
  "files_created": [
    "C:\\Users\\sa2005599\\Desktop\\المساعد القانوني\\الكود\\scripts\\learned_styles\\drafting_style_guide.json",
    "C:\\Users\\sa2005599\\Desktop\\المساعد القانوني\\الكود\\scripts\\learned_styles\\overnight_results.json",
    "C:\\Users\\sa2005599\\Desktop\\المساعد القانوني\\الكود\\scripts\\overnight_learning.log"
  ]
}